api.py
auth.py
cli.py
download.py
main.py
network.py
sync.py
sync_daemon.py
upload.py
mailru_cloud_cli-1.4.3.dist-info/licenses/LICENSE
mailru_cloud_cli-1.4.3.dist-info/METADATA
mailru_cloud_cli-1.4.3.dist-info/WHEEL
mailru_cloud_cli-1.4.3.dist-info/entry_points.txt
mailru_cloud_cli-1.4.3.dist-info/top_level.txt
mailru_cloud_cli-1.4.3.dist-info/RECORD
