Metadata-Version: 2.4
Name: mailru-cloud-cli
Version: 1.4.3
Summary: Неофициальный CLI-клиент для Mail.ru Cloud (WebDAV)
Author-email: mueqee <you@example.com>
License-Expression: MIT
Project-URL: Homepage, https://github.com/mueqee/mailrucloud
Project-URL: Changelog, https://github.com/mueqee/mailrucloud/blob/main/CHANGELOG.md
Classifier: Programming Language :: Python :: 3
Classifier: Operating System :: OS Independent
Classifier: Environment :: Console
Requires-Python: >=3.10
License-File: LICENSE
Requires-Dist: click>=8
Requires-Dist: webdavclient3>=3.14
Requires-Dist: pytest>=8
Requires-Dist: rich>=12.0.0
Dynamic: license-file
